givemecontext/__init__.py
givemecontext/automations/directory_logger.py
givemecontext/automations/format_check_test.py
givemecontext/automations/format_check_test.sh
givemecontext/config.py
givemecontext/decorators/to_log.py
givemecontext/givemecontext.py
givemecontext/utils/logging_level_resolver.py
givemecontext/utils/shell_script_runner.py
givemecontext-0.1.4.dist-info/METADATA
givemecontext-0.1.4.dist-info/WHEEL
givemecontext-0.1.4.dist-info/RECORD
